[
    {
        "color":"Rouge",
        "link":"rPrend2.png",
        "effect":"Prend2"
    },
    {
        "color":"Rouge",
        "link":"rPrend2.png",
        "effect":"Prend2"
    },
    {
        "color":"Vert",
        "link":"vPrend2.png",
        "effect":"Prend2"
    },
    {
        "color":"Vert",
        "link":"vPrend2.png",
        "effect":"Prend2"
    },
    {
        "color":"Bleue",
        "link":"bPrend2.png",
        "effect":"Prend2"
    },
    {
        "color":"Bleue",
        "link":"bPrend2.png",
        "effect":"Prend2"
    },
    {
        "color":"Jaune",
        "link":"jPrend2.png",
        "effect":"Prend2"
    },
    {
        "color":"Jaune",
        "link":"jPrend2.png",
        "effect":"Prend2"
    },
    {
        "color":"Rouge",
        "link":"rInversion.png",
        "effect":"Inversion"
    },
    {
        "color":"Rouge",
        "link":"rInversion.png",
        "effect":"Inversion"
    },
    {
        "color":"Vert",
        "link":"vInversion.png",
        "effect":"Inversion"
    },
    {
        "color":"Vert",
        "link":"vInversion.png",
        "effect":"Inversion"
    },
    {
        "color":"Bleue",
        "link":"bInversion.png",
        "effect":"Inversion"
    },
    {
        "color":"Bleue",
        "link":"bInversion.png",
        "effect":"Inversion"
    },
    {
        "color":"Jaune",
        "link":"jInversion.png",
        "effect":"Inversion"
    },
    {
        "color":"Jaune",
        "link":"jInversion.png",
        "effect":"Inversion"
    },
    {
        "color":"Rouge",
        "link":"rPasseTour.png",
        "effect":"PasseTonTour"
    },
    {
        "color":"Rouge",
        "link":"rPasseTour.png",
        "effect":"PasseTonTour"
    },
    {
        "color":"Vert",
        "link":"vPasseTour.png",
        "effect":"PasseTonTour"
    },
    {
        "color":"Vert",
        "link":"vPasseTour.png",
        "effect":"PasseTonTour"
    },
    {
        "color":"Bleue",
        "link":"bPasseTour.png",
        "effect":"PasseTonTour"
    },
    {
        "color":"Bleue",
        "link":"bPasseTour.png",
        "effect":"PasseTonTour"
    },
    {
        "color":"Jaune",
        "link":"jPasseTour.png",
        "effect":"PasseTonTour"
    },
    {
        "color":"Jaune",
        "link":"jPasseTour.png",
        "effect":"PasseTonTour"
    },
    {
        "color":"Multi",
        "link":"joker.png",
        "effect":"Joker"
    },
    {
        "color":"Multi",
        "link":"joker.png",
        "effect":"Joker"
    },
    {
        "color":"Multi",
        "link":"joker.png",
        "effect":"Joker"
    },
    {
        "color":"Multi",
        "link":"joker.png",
        "effect":"Joker"
    },
    {
        "color":"Multi",
        "link":"superjoker.png",
        "effect":"SuperJoker"
    },
    {
        "color":"Multi",
        "link":"superjoker.png",
        "effect":"SuperJoker"
    },
    {
        "color":"Multi",
        "link":"superjoker.png",
        "effect":"SuperJoker"
    },
    {
        "color":"Multi",
        "link":"superjoker.png",
        "effect":"SuperJoker"
    }
]
